resnetcarvanapkg/__init__.py
resnetcarvanapkg/main.py
resnetcarvanapkg-0.0.2.dist-info/LICENSE
resnetcarvanapkg-0.0.2.dist-info/METADATA
resnetcarvanapkg-0.0.2.dist-info/WHEEL
resnetcarvanapkg-0.0.2.dist-info/top_level.txt
resnetcarvanapkg-0.0.2.dist-info/RECORD
