Metadata-Version: 2.1
Name: resnetcarvanapkg
Version: 0.0.2
Summary: a package that kinda works
Author-email: sliu23009@gmail.com
Classifier: Programming Language :: Python :: 3
Classifier: License :: OSI Approved :: MIT License
Classifier: Operating System :: OS Independent
Requires-Python: >=3.6
License-File: LICENSE
